CHANGELOG.txt
LICENCE.txt
MANIFEST.in
README.txt
setup.py
ThomCode/TEST.py
ThomCode/__init__.py
ThomCode/higher_lower_game.py
ThomCode.egg-info/PKG-INFO
ThomCode.egg-info/SOURCES.txt
ThomCode.egg-info/dependency_links.txt
ThomCode.egg-info/top_level.txt