Metadata-Version: 1.1
Name: ThomCode
Version: 1.0.8
Summary: Solution to all your problems
Home-page: UNKNOWN
Author: Thom van Hamburg
Author-email: Thomniville@gmail.com
License: MIT
Keywords: ThomCode,pi,sqrt,factorial,prime,list,biominal coefficient,geometry,matrix,fibonacci sequence,game
Platform: UNKNOWN
Classifier: Development Status :: 5 - Production/Stable
Classifier: Intended Audience :: Education
Classifier: Operating System :: Microsoft :: Windows :: Windows 10
Classifier: License :: OSI Approved :: MIT License
Classifier: Programming Language :: Python :: 3
